<?xml version="1.0" encoding="UTF-8"?>
<!DOCTYPE sect1 PUBLIC "-//OASIS//DTD DocBook XML V4.5//EN"
  "http://www.oasis-open.org/docbook/xml/4.5/docbookx.dtd" [
  <!ENTITY % general-entities SYSTEM "../general.ent">
  %general-entities;
]>

<sect1 id="ch-intro-changelog">
  <?dbhtml filename="changelog.html"?>

  <title>Журнал изменений</title>

  <para>Это версия &version; книги Linux From Scratch от &releasedate;. Если
  этой книге больше шести месяцев, возможно, уже доступна более новая, улучшенная
  версия. Чтобы узнать это, проверьте одно из зеркал <ulink url="&lfs-root;mirrors.html"/>.</para>

  <para>Ниже приведен список изменений, внесенных с момента предыдущего выпуска
  книги.</para>

  <itemizedlist>
    <title>Список изменений:</title>

<!-- Changelog template

    <listitem>
      <para>Date</para>
      <itemizedlist>
        <listitem>
          <para>[name] - New changelog entry.</para>
        </listitem>
        <listitem>
          <para>[name] - Previous changelog entry.</para>
        </listitem>
      </itemizedlist>
    </listitem>

    Note:  If a change is only specific to sysv or systemd, then use
    <listitem revision="sysv"> or <listitem revision="systemd"> as
    appropriate for the entry or if needed the entire day's listitem.
    -->

    <listitem>
      <para>2024-05-01</para>
      <itemizedlist>
        <listitem>
          <para>[bdubbs] - Add security fix to glibc. Fixes
          <ulink url='&lfs-ticket-root;5481'>#5481</ulink>.</para>
        </listitem>
        <listitem>
          <para>[bdubbs] - Update to linux-6.8.8. Fixes
          <ulink url='&lfs-ticket-root;5480'>#5480</ulink>.</para>
        </listitem>
        <listitem>
          <para>[bdubbs] - Update to ncurses-6.5. Fixes
          <ulink url='&lfs-ticket-root;5483'>#5483</ulink>.</para>
        </listitem>
      </itemizedlist>
    </listitem>

    <listitem revision='sysv'>
      <para>2024-04-16</para>
      <itemizedlist>
        <listitem>
          <para>[bdubbs] - Make minor change to ifup script output text.</para>
        </listitem>
      </itemizedlist>
    </listitem>

    <listitem>
      <para>2024-04-15</para>
      <itemizedlist>
        <listitem>
          <para>[bdubbs] - Update to setuptools-69.5.1. Fixes
          <ulink url='&lfs-ticket-root;5478'>#5478</ulink>.</para>
        </listitem>
        <listitem>
          <para>[bdubbs] - Update to python3-3.12.3. Fixes
          <ulink url='&lfs-ticket-root;5476'>#5476</ulink>.</para>
        </listitem>
        <listitem>
          <para>[bdubbs] - Update to openssl-3.3.0. Fixes
          <ulink url='&lfs-ticket-root;5475'>#5475</ulink>.</para>
        </listitem>
        <listitem>
          <para>[bdubbs] - Update to ninja-1.12.0. Fixes
          <ulink url='&lfs-ticket-root;5477'>#5477</ulink>.</para>
        </listitem>
        <listitem>
          <para>[bdubbs] - Update to man-db-2.12.1. Fixes
          <ulink url='&lfs-ticket-root;5474'>#5474</ulink>.</para>
        </listitem>
        <listitem>
          <para>[bdubbs] - Update to linux-6.8.6. Fixes
          <ulink url='&lfs-ticket-root;5472'>#5472</ulink>.</para>
        </listitem>
        <listitem>
          <para>[bdubbs] - Update to iana-etc-20240412. Addresses
          <ulink url='&lfs-ticket-root;5006'>#5006</ulink>.</para>
        </listitem>
        <listitem>
          <para>[bdubbs] - Update to vim-9.1.0330. Addresses
          <ulink url='&lfs-ticket-root;4500'>#4500</ulink>.</para>
        </listitem>
      </itemizedlist>
    </listitem>

    <listitem>
      <para>2024-03-31</para>
      <itemizedlist>
        <listitem>
          <para>[bdubbs] - Update to iana-etc-20240318. Addresses
          <ulink url='&lfs-ticket-root;5006'>#5006</ulink>.</para>
        </listitem>
        <listitem>
          <para>[bdubbs] - Update to zstd-1.5.6. Fixes
          <ulink url='&lfs-ticket-root;5468'>#5468</ulink>.</para>
        </listitem>
        <listitem>
          <para>[bdubbs] - Update to util-linux-2.40. Fixes
          <ulink url='&lfs-ticket-root;5430'>#5430</ulink>.</para>
        </listitem>
        <listitem>
          <para>[bdubbs] - Update to shadow-4.15.1. Fixes
          <ulink url='&lfs-ticket-root;5465'>#5465</ulink>.</para>
        </listitem>
        <listitem>
          <para>[bdubbs] - Update to pkgconf-2.2.0. Fixes
          <ulink url='&lfs-ticket-root;5469'>#5469</ulink>.</para>
        </listitem>
        <listitem>
          <para>[bdubbs] - Update to linux-6.8.2. Fixes
          <ulink url='&lfs-ticket-root;5467'>#5467</ulink>.</para>
        </listitem>
        <listitem>
          <para>[bdubbs] - Update to coreutils-9.5. Fixes
          <ulink url='&lfs-ticket-root;5470'>#5470</ulink>.</para>
        </listitem>
      </itemizedlist>
    </listitem>

    <listitem>
      <para>2024-03-29</para>
      <itemizedlist>
        <listitem>
           <para>[bdubbs] - Revert to xz-5.4.6 due to upstream 
           compromise.</para>
        </listitem>
      </itemizedlist>
    </listitem>

    <listitem revision='sysv'>
      <para>2024-03-25</para>
      <itemizedlist>
        <listitem>
          <para>[timtas] - Update to sysvinit-3.09. Fixes
          <ulink url="&lfs-ticket-root;5466">#5466</ulink>.</para>
        </listitem>
      </itemizedlist>
    </listitem>

    <listitem>
      <para>2024-03-19</para>
      <itemizedlist>
        <listitem>
          <para>[renodr] - Update to iproute2-6.8.0. Fixes
          <ulink url="&lfs-ticket-root;5458">#5458</ulink>.</para>
        </listitem>
        <listitem>
          <para>[renodr] - Update to man-pages-6.7. Fixes
          <ulink url="&lfs-ticket-root;5464">#5464</ulink>.</para>
        </listitem>
        <listitem>
          <para>[renodr] - Update to Linux-6.8.1. Fixes
          <ulink url="&lfs-ticket-root;5453">#5453</ulink>.</para>
        </listitem>
        <listitem>
          <para>[renodr] - Added LZ4 to the book. Fixes
          <ulink url="&lfs-ticket-root;5463">#5463</ulink>.</para>
        </listitem>
      </itemizedlist>
    </listitem>

    <listitem>
      <para>2024-03-15</para>
      <itemizedlist>
        <listitem>
          <para>[bdubbs] - Update to wheel-0.43.0. Fixes
          <ulink url='&lfs-ticket-root;5459'>#5459</ulink>.</para>
        </listitem>
        <listitem>
          <para>[bdubbs] - Update to setuptools-69.2.0 (Python module). Fixes
          <ulink url='&lfs-ticket-root;5462'>#5462</ulink>.</para>
        </listitem>
        <listitem>
          <para>[bdubbs] - Update to meson-1.4.0. Fixes
          <ulink url='&lfs-ticket-root;5460'>#5460</ulink>.</para>
        </listitem>
        <listitem>
          <para>[bdubbs] - Update to expat-2.6.2 (Security fix). Fixes
          <ulink url='&lfs-ticket-root;5461'>#5461</ulink>.</para>
        </listitem>
        <listitem>
          <para>[bdubbs] - Update to iana-etc-20240305. Addresses
          <ulink url='&lfs-ticket-root;5006'>#5006</ulink>.</para>
        </listitem>
        <listitem>
          <para>[bdubbs] - Update to vim-9.1.0161. Addresses
          <ulink url='&lfs-ticket-root;4500'>#4500</ulink>.</para>
        </listitem>
        <listitem>
          <para>[bdubbs] - Update to xz-5.6.1. Fixes
          <ulink url='&lfs-ticket-root;5457'>#5457</ulink>.</para>
        </listitem>
        <listitem>
          <para>[bdubbs] - Update to shadow-4.15.0. Fixes
          <ulink url='&lfs-ticket-root;5456'>#5456</ulink>.</para>
        </listitem>
        <listitem>
          <para>[bdubbs] - Update to psmisc-23.7. Fixes
          <ulink url='&lfs-ticket-root;5454'>#5454</ulink>.</para>
        </listitem>
        <listitem>
          <para>[bdubbs] - Update to kmod-32. Fixes
          <ulink url='&lfs-ticket-root;5455'>#5455</ulink>.</para>
        </listitem>
        <listitem>
          <para>[bdubbs] - Update to elfutils-0.191. Fixes
          <ulink url='&lfs-ticket-root;5451'>#5451</ulink>.</para>
        </listitem>
      </itemizedlist>
    </listitem>

    <listitem>
      <para>2024-03-02</para>
      <itemizedlist>
        <listitem>
          <para>[bdubbs] - Update to iana-etc-20240222. Addresses
          <ulink url='&lfs-ticket-root;5006'>#5006</ulink>.</para>
        </listitem>
        <listitem>
          <para>[bdubbs] - Update to vim-9.1.0145. Addresses
          <ulink url='&lfs-ticket-root;4500'>#4500</ulink>.</para>
        </listitem>
        <listitem>
          <para>[bdubbs] - Update to xz-5.6.0. Fixes
          <ulink url='&lfs-ticket-root;5447'>#5447</ulink>.</para>
        </listitem>
        <listitem>
          <para>[bdubbs] - Update to tcl-8.6.14. Fixes
          <ulink url='&lfs-ticket-root;5448'>#5448</ulink>.</para>
        </listitem>
        <listitem>
          <para>[bdubbs] - Update to shadow-4.14.6. Fixes
          <ulink url='&lfs-ticket-root;5450'>#5450</ulink>.</para>
        </listitem>
        <listitem>
          <para>[bdubbs] - Update to setuptools-69.1.1. Fixes
          <ulink url='&lfs-ticket-root;5446'>#5446</ulink>.</para>
        </listitem>
        <listitem>
          <para>[bdubbs] - Update to linux-6.7.7. Fixes
          <ulink url='&lfs-ticket-root;5444'>#5444</ulink>.</para>
        </listitem>
        <listitem>
          <para>[bdubbs] - Update to libffi-3.4.6. Fixes
          <ulink url='&lfs-ticket-root;5443'>#5443</ulink>.</para>
        </listitem>
        <listitem>
          <para>[bdubbs] - Update to gettext-0.22.5. Fixes
          <ulink url='&lfs-ticket-root;5445'>#5445</ulink>.</para>
        </listitem>
        <listitem>
          <para>[bdubbs] - Update to expat-2.6.1. Fixes
          <ulink url='&lfs-ticket-root;5449'>#5449</ulink>.</para>
        </listitem>
      </itemizedlist>
    </listitem>

    <listitem>
      <para>2024-03-01</para>
      <itemizedlist>
        <listitem>
          <para>[bdubbs] - LFS-12.1 released.</para>
        </listitem>
      </itemizedlist>
    </listitem>

  </itemizedlist>
</sect1>
